ocrmypdf_easyocr/__init__.py
ocrmypdf_easyocr/_cv.py
ocrmypdf_easyocr/_easyocr.py
ocrmypdf_easyocr/_pdf.py
ocrmypdf_easyocr/pdf.ttf
ocrmypdf_easyocr/py.typed
ocrmypdf_easyocr-0.2.1.dist-info/METADATA
ocrmypdf_easyocr-0.2.1.dist-info/WHEEL
ocrmypdf_easyocr-0.2.1.dist-info/entry_points.txt
ocrmypdf_easyocr-0.2.1.dist-info/licenses/LICENSE
ocrmypdf_easyocr-0.2.1.dist-info/RECORD
