Metadata-Version: 2.3
Name: ocrmypdf-easyocr
Version: 0.2.1
Summary: Plugin to run OCRmyPDF with the EasyOCR engine
Project-URL: Homepage, https://github.com/ocrmypdf/OCRmyPDF-EasyOCR
Project-URL: Repository, https://github.com/ocrmypdf/OCRmyPDF-EasyOCR.git
Author-email: "James R. Barlow" <james@purplerock.ca>
License: MIT
License-File: LICENSE
Requires-Python: >=3.10
Requires-Dist: easyocr>=1.7.0
Requires-Dist: numpy>=1.20
Requires-Dist: ocrmypdf>=14.2.1
Requires-Dist: opencv-python-headless>=4.8.0.74
Requires-Dist: pillow>=10.0.1
Requires-Dist: torch
Provides-Extra: dev
Requires-Dist: ruff>=0.0.272; extra == 'dev'
Provides-Extra: test
Requires-Dist: pytest>=6.2.5; extra == 'test'
